hkobservatory.py
hkobservatory-1.0.6.dist-info/DESCRIPTION.rst
hkobservatory-1.0.6.dist-info/METADATA
hkobservatory-1.0.6.dist-info/RECORD
hkobservatory-1.0.6.dist-info/WHEEL
hkobservatory-1.0.6.dist-info/metadata.json
hkobservatory-1.0.6.dist-info/top_level.txt
